{"type":"FeatureCollection","totalFeatures":71,"features":[{"type":"Feature","id":"age_household_ref_person_2011.1","geometry":null,"properties":{"objectid":1,"state_code":"4","bbox":[-34.9424,138.5767,-34.8986,138.6245]}},{"type":"Feature","id":"age_household_ref_person_2011.2","geometry":null,"properties":{"objectid":2,"state_code":"4","bbox":[-35.1216,138.6652,-34.6805,139.044]}},{"type":"Feature","id":"age_household_ref_person_2011.3","geometry":null,"properties":{"objectid":3,"state_code":"4","bbox":[-35.5626,138.5158,-35.1128,139.1583]}},{"type":"Feature","id":"age_household_ref_person_2011.4","geometry":null,"properties":{"objectid":4,"state_code":"4","bbox":[-28.1174,129.0013,-25.9986,133.7449]}},{"type":"Feature","id":"age_household_ref_person_2011.5","geometry":null,"properties":{"objectid":5,"state_code":"4","bbox":[-34.8153,138.7514,-34.4117,139.1719]}},{"type":"Feature","id":"age_household_ref_person_2011.6","geometry":null,"properties":{"objectid":6,"state_code":"4","bbox":[-34.1216,137.7013,-33.4681,138.1449]}},{"type":"Feature","id":"age_household_ref_person_2011.7","geometry":null,"properties":{"objectid":7,"state_code":"4","bbox":[-34.4563,140.3202,-34.1194,140.667]}},{"type":"Feature","id":"age_household_ref_person_2011.8","geometry":null,"properties":{"objectid":8,"state_code":"4","bbox":[-34.9762,138.6157,-34.9127,138.701]}},{"type":"Feature","id":"age_household_ref_person_2011.9","geometry":null,"properties":{"objectid":9,"state_code":"4","bbox":[-34.9139,138.6471,-34.857,138.7238]}},{"type":"Feature","id":"age_household_ref_person_2011.10","geometry":null,"properties":{"objectid":10,"state_code":"4","bbox":[-32.5426,133.2127,-31.7521,134.513]}},{"type":"Feature","id":"age_household_ref_person_2011.11","geometry":null,"properties":{"objectid":11,"state_code":"4","bbox":[-34.9514,138.4757,-34.85,138.5879]}},{"type":"Feature","id":"age_household_ref_person_2011.12","geometry":null,"properties":{"objectid":12,"state_code":"4","bbox":[-34.3706,138.531,-33.6587,138.9758]}},{"type":"Feature","id":"age_household_ref_person_2011.13","geometry":null,"properties":{"objectid":13,"state_code":"4","bbox":[-33.993,135.9069,-33.3286,136.6709]}},{"type":"Feature","id":"age_household_ref_person_2011.14","geometry":null,"properties":{"objectid":14,"state_code":"4","bbox":[-29.0517,134.6941,-28.971,134.8097]}},{"type":"Feature","id":"age_household_ref_person_2011.15","geometry":null,"properties":{"objectid":15,"state_code":"4","bbox":[-34.0976,137.5079,-33.7881,137.9186]}},{"type":"Feature","id":"age_household_ref_person_2011.16","geometry":null,"properties":{"objectid":16,"state_code":"4","bbox":[-33.9403,134.2822,-33.1384,135.9081]}},{"type":"Feature","id":"age_household_ref_person_2011.17","geometry":null,"properties":{"objectid":17,"state_code":"4","bbox":[-32.5271,137.923,-31.7397,138.7546]}},{"type":"Feature","id":"age_household_ref_person_2011.18","geometry":null,"properties":{"objectid":18,"state_code":"4","bbox":[-33.8774,136.4974,-33.3259,137.3856]}},{"type":"Feature","id":"age_household_ref_person_2011.19","geometry":null,"properties":{"objectid":19,"state_code":"4","bbox":[-34.6705,138.68,-34.5716,138.7845]}},{"type":"Feature","id":"age_household_ref_person_2011.20","geometry":null,"properties":{"objectid":20,"state_code":"4","bbox":[-34.3352,138.675,-33.0976,139.358]}},{"type":"Feature","id":"age_household_ref_person_2011.21","geometry":null,"properties":{"objectid":21,"state_code":"4","bbox":[-38.0626,140.2928,-37.6102,140.9736]}},{"type":"Feature","id":"age_household_ref_person_2011.22","geometry":null,"properties":{"objectid":22,"state_code":"4","bbox":[-35.0422,138.5086,-34.9627,138.5378]}},{"type":"Feature","id":"age_household_ref_person_2011.23","geometry":null,"properties":{"objectid":23,"state_code":"4","bbox":[-36.0866,136.5329,-35.5612,138.1349]}},{"type":"Feature","id":"age_household_ref_person_2011.24","geometry":null,"properties":{"objectid":24,"state_code":"4","bbox":[-35.2918,139.6196,-34.5651,140.4301]}},{"type":"Feature","id":"age_household_ref_person_2011.25","geometry":null,"properties":{"objectid":25,"state_code":"4","bbox":[-33.3312,135.825,-32.7651,136.8109]}},{"type":"Feature","id":"age_household_ref_person_2011.26","geometry":null,"properties":{"objectid":26,"state_code":"4","bbox":[-37.0329,139.67,-36.2487,140.4318]}},{"type":"Feature","id":"age_household_ref_person_2011.27","geometry":null,"properties":{"objectid":27,"state_code":"4","bbox":[-34.6321,138.56,-34.1876,139.1274]}},{"type":"Feature","id":"age_household_ref_person_2011.28","geometry":null,"properties":{"objectid":28,"state_code":"4","bbox":[-35.0376,135.028,-33.9386,136.3743]}},{"type":"Feature","id":"age_household_ref_person_2011.29","geometry":null,"properties":{"objectid":29,"state_code":"4","bbox":[-35.0196,139.6006,-33.9436,140.9663]}},{"type":"Feature","id":"age_household_ref_person_2011.30","geometry":null,"properties":{"objectid":30,"state_code":"4","bbox":[-34.6763,138.2252,-34.3444,138.6304]}},{"type":"Feature","id":"age_household_ref_person_2011.31","geometry":null,"properties":{"objectid":31,"state_code":"4","bbox":[-30.764,129.0014,-28.1159,133.0065]}},{"type":"Feature","id":"age_household_ref_person_2011.32","geometry":null,"properties":{"objectid":32,"state_code":"4","bbox":[-35.0933,138.4857,-34.9585,138.5762]}},{"type":"Feature","id":"age_household_ref_person_2011.33","geometry":null,"properties":{"objectid":33,"state_code":"4","bbox":[-35.0305,138.9751,-33.8008,139.8577]}},{"type":"Feature","id":"age_household_ref_person_2011.34","geometry":null,"properties":{"objectid":34,"state_code":"4","bbox":[-35.0505,138.563,-34.9633,138.6814]}},{"type":"Feature","id":"age_household_ref_person_2011.35","geometry":null,"properties":{"objectid":35,"state_code":"4","bbox":[-35.2433,138.6947,-34.8948,139.044]}},{"type":"Feature","id":"age_household_ref_person_2011.36","geometry":null,"properties":{"objectid":36,"state_code":"4","bbox":[-37.8551,140.7376,-37.7943,140.8262]}},{"type":"Feature","id":"age_household_ref_person_2011.37","geometry":null,"properties":{"objectid":37,"state_code":"4","bbox":[-33.1131,137.9025,-32.3231,138.4402]}},{"type":"Feature","id":"age_household_ref_person_2011.38","geometry":null,"properties":{"objectid":38,"state_code":"4","bbox":[-35.4717,139.0194,-34.9287,139.6224]}},{"type":"Feature","id":"age_household_ref_person_2011.39","geometry":null,"properties":{"objectid":39,"state_code":"4","bbox":[-37.3219,140.0838,-36.669,140.972]}},{"type":"Feature","id":"age_household_ref_person_2011.40","geometry":null,"properties":{"objectid":40,"state_code":"4","bbox":[-33.6591,138.1637,-32.9423,138.7912]}},{"type":"Feature","id":"age_household_ref_person_2011.41","geometry":null,"properties":{"objectid":41,"state_code":"4","bbox":[-34.933,138.6128,-34.883,138.6583]}},{"type":"Feature","id":"age_household_ref_person_2011.42","geometry":null,"properties":{"objectid":42,"state_code":"4","bbox":[-35.3503,138.4421,-35.0233,138.7134]}},{"type":"Feature","id":"age_household_ref_person_2011.43","geometry":null,"properties":{"objectid":43,"state_code":"4","bbox":[-32.9433,138.4392,-32.1203,138.8902]}},{"type":"Feature","id":"age_household_ref_person_2011.44","geometry":null,"properties":{"objectid":44,"state_code":"4","bbox":[-33.1018,138.6979,-32.594,139.3543]}},{"type":"Feature","id":"age_household_ref_person_2011.45","geometry":null,"properties":{"objectid":45,"state_code":"4","bbox":[-34.7754,138.4362,-34.613,138.848]}},{"type":"Feature","id":"age_household_ref_person_2011.46","geometry":null,"properties":{"objectid":46,"state_code":"4","bbox":[-34.8895,138.4758,-34.7631,138.6695]}},{"type":"Feature","id":"age_household_ref_person_2011.47","geometry":null,"properties":{"objectid":47,"state_code":"4","bbox":[-32.8775,137.5959,-32.3548,137.9652]}},{"type":"Feature","id":"age_household_ref_person_2011.48","geometry":null,"properties":{"objectid":48,"state_code":"4","bbox":[-34.7697,135.8214,-34.6874,135.8936]}},{"type":"Feature","id":"age_household_ref_person_2011.49","geometry":null,"properties":{"objectid":49,"state_code":"4","bbox":[-33.6263,137.8108,-33.104,138.4033]}},{"type":"Feature","id":"age_household_ref_person_2011.50","geometry":null,"properties":{"objectid":50,"state_code":"4","bbox":[-34.8992,138.5808,-34.8699,138.62]}},{"type":"Feature","id":"age_household_ref_person_2011.51","geometry":null,"properties":{"objectid":51,"state_code":"4","bbox":[-34.3234,140.5864,-33.9627,140.9642]}},{"type":"Feature","id":"age_household_ref_person_2011.52","geometry":null,"properties":{"objectid":52,"state_code":"4","bbox":[-37.3399,139.7364,-37.0325,140.2437]}},{"type":"Feature","id":"age_household_ref_person_2011.53","geometry":null,"properties":{"objectid":53,"state_code":"4","bbox":[-30.6235,136.843,-30.4743,136.9245]}},{"type":"Feature","id":"age_household_ref_person_2011.54","geometry":null,"properties":{"objectid":54,"state_code":"4","bbox":[-34.8444,138.5173,-34.6922,138.6993]}},{"type":"Feature","id":"age_household_ref_person_2011.55","geometry":null,"properties":{"objectid":55,"state_code":"4","bbox":[-35.748,140.0744,-34.9867,140.9662]}},{"type":"Feature","id":"age_household_ref_person_2011.56","geometry":null,"properties":{"objectid":56,"state_code":"4","bbox":[-33.2452,133.9656,-32.231,135.1368]}},{"type":"Feature","id":"age_household_ref_person_2011.57","geometry":null,"properties":{"objectid":57,"state_code":"4","bbox":[-36.7024,140.046,-35.7422,140.9689]}},{"type":"Feature","id":"age_household_ref_person_2011.58","geometry":null,"properties":{"objectid":58,"state_code":"4","bbox":[-34.8692,138.6597,-34.7343,138.7802]}},{"type":"Feature","id":"age_household_ref_person_2011.59","geometry":null,"properties":{"objectid":59,"state_code":"4","bbox":[-36.2539,138.8862,-35.1829,140.5204]}},{"type":"Feature","id":"age_household_ref_person_2011.60","geometry":null,"properties":{"objectid":60,"state_code":"4","bbox":[-34.5438,135.7773,-33.8501,136.4956]}},{"type":"Feature","id":"age_household_ref_person_2011.61","geometry":null,"properties":{"objectid":61,"state_code":"4","bbox":[-34.9673,138.5719,-34.9406,138.6441]}},{"type":"Feature","id":"age_household_ref_person_2011.62","geometry":null,"properties":{"objectid":62,"state_code":"4","bbox":[-35.643,138.4373,-35.3891,138.6549]}},{"type":"Feature","id":"age_household_ref_person_2011.63","geometry":null,"properties":{"objectid":63,"state_code":"4","bbox":[-34.3891,138.0844,-33.6258,138.7047]}},{"type":"Feature","id":"age_household_ref_person_2011.64","geometry":null,"properties":{"objectid":64,"state_code":"4","bbox":[-34.9095,138.5973,-34.8794,138.6352]}},{"type":"Feature","id":"age_household_ref_person_2011.65","geometry":null,"properties":{"objectid":65,"state_code":"4","bbox":[-37.84,139.8684,-37.176,140.9739]}},{"type":"Feature","id":"age_household_ref_person_2011.66","geometry":null,"properties":{"objectid":66,"state_code":"4","bbox":[-34.9759,138.503,-34.9091,138.5829]}},{"type":"Feature","id":"age_household_ref_person_2011.67","geometry":null,"properties":{"objectid":67,"state_code":"4","bbox":[-33.3262,137.2788,-32.7652,137.8106]}},{"type":"Feature","id":"age_household_ref_person_2011.68","geometry":null,"properties":{"objectid":68,"state_code":"4","bbox":[-33.3333,134.8205,-32.6216,135.9629]}},{"type":"Feature","id":"age_household_ref_person_2011.69","geometry":null,"properties":{"objectid":69,"state_code":"4","bbox":[-35.6651,138.0938,-35.3227,138.5907]}},{"type":"Feature","id":"age_household_ref_person_2011.70","geometry":null,"properties":{"objectid":70,"state_code":"4","bbox":[-35.3782,136.8219,-34.0849,138.1278]}},{"type":"Feature","id":"age_household_ref_person_2011.71","geometry":null,"properties":{"objectid":71,"state_code":"4","bbox":[-35.7357,129.0013,-25.9961,141.003]}}],"crs":null}